matrixlink/__init__.py
matrixlink/a2a.py
matrixlink/config.py
matrixlink/discovery.py
matrixlink/errors.py
matrixlink/orchestrator.py
matrixlink/providers.py
matrixlink/sse.py
matrixlink/utils.py
matrixlink-0.1.0.dist-info/METADATA
matrixlink-0.1.0.dist-info/WHEEL
matrixlink-0.1.0.dist-info/top_level.txt
matrixlink-0.1.0.dist-info/RECORD
