Metadata-Version: 2.4
Name: matrixlink
Version: 0.1.0
Summary: MatrixLink — Client for MCP Gateway discovery, Orchestrator invoke, and A2A agent messaging.
Author-email: MatrixHub <contact@ruslanmv.com>
License: Apache-2.0
Project-URL: Homepage, https://github.com/agent-matrix/matrixlink
Project-URL: Repository, https://github.com/agent-matrix/matrixlink
Project-URL: Issues, https://github.com/agent-matrix/matrixlink/issues
Project-URL: Documentation, https://agent-matrix.github.io/matrixlink/
Keywords: mcp,a2a,agents,gateway,discovery,orchestrator,matrixhub
Classifier: Development Status :: 4 - Beta
Classifier: Intended Audience :: Developers
Classifier: License :: OSI Approved :: Apache Software License
Classifier: Programming Language :: Python :: 3
Classifier: Programming Language :: Python :: 3 :: Only
Classifier: Programming Language :: Python :: 3.10
Classifier: Programming Language :: Python :: 3.11
Classifier: Programming Language :: Python :: 3.12
Classifier: Typing :: Typed
Requires-Python: >=3.10
Requires-Dist: httpx<0.29,>=0.27
Requires-Dist: sseclient-py<2.0,>=1.8
Requires-Dist: python-dotenv<2.0,>=1.0
Requires-Dist: truststore>=0.8; python_version >= "3.11"
Requires-Dist: tomli>=2.0.1; python_version < "3.11"
